openmeasure/__init__.py
openmeasure/cokriging.py
openmeasure/dgpr.py
openmeasure/gpr.py
openmeasure/sparse_sensing.py
openmeasure/utils.py
openmeasure-0.4.1.dist-info/licenses/LICENSE.txt
openmeasure-0.4.1.dist-info/METADATA
openmeasure-0.4.1.dist-info/WHEEL
openmeasure-0.4.1.dist-info/top_level.txt
openmeasure-0.4.1.dist-info/RECORD
