Metadata-Version: 2.4
Name: OpenMEASURE
Version: 0.4.1
Summary: Python package for soft sensing applications
Author-email: Alberto Procacci <alberto.procacci@ulb.be>
Project-URL: Homepage, https://github.com/burn_research/OpenMEASURE
Classifier: Programming Language :: Python :: 3
Classifier: License :: OSI Approved :: MIT License
Classifier: Operating System :: OS Independent
Requires-Python: >=3.8
License-File: LICENSE.txt
Requires-Dist: numpy>=1.24.2
Requires-Dist: scipy>=1.10.1
Requires-Dist: gpytorch>=1.9.1
Requires-Dist: cvxpy>=1.3.1
Requires-Dist: openmdao>=3.15.0
Requires-Dist: pyvista>=0.41.1
Dynamic: license-file
